get_image_document/__init__.py
get_image_document/download.py
get_image_document/funcs/__init__.py
get_image_document/funcs/image_getter.py
get_image_document/funcs/image_manage.py
get_image_document/funcs/word.py
get_image_document/main.py
get_image_document-0.3.4.dist-info/entry_points.txt
get_image_document-0.3.4.dist-info/METADATA
get_image_document-0.3.4.dist-info/WHEEL
get_image_document-0.3.4.dist-info/RECORD
